jira_history_api/__init__.py
jira_history_api/__main__.py
jira_history_api/cli.py
jira_history_api/jira_history.py
jira_history_api/utils.py
jira_history_api-0.4.0.dist-info/LICENSE.txt
jira_history_api-0.4.0.dist-info/METADATA
jira_history_api-0.4.0.dist-info/WHEEL
jira_history_api-0.4.0.dist-info/entry_points.txt
jira_history_api-0.4.0.dist-info/top_level.txt
jira_history_api-0.4.0.dist-info/zip-safe
jira_history_api-0.4.0.dist-info/RECORD
