Metadata-Version: 2.1
Name: jira-history-api
Version: 0.4.0
Summary: Python JIRA Historical Search API
Home-page: https://github.com/KevinDeJong-TomTom/jira-history-api
Author: Kevin de Jong
Author-email: KevinDeJong@tomtom.com
License: Apache License 2.0
Download-URL: https://github.com/KevinDeJong-TomTom/jira-history-api
Keywords: atlassian jira core software rest api history historical search
Platform: UNKNOWN
Requires-Python: >=3.5
Requires-Dist: Click (<8,>=7)
Requires-Dist: atlassian-python-api (==1.17.2)
